csutl/__init__.py
csutl/__main__.py
csutl/api.py
csutl/cli.py
csutl/common.py
csutl/exception.py
csutl-0.2.0.dist-info/licenses/LICENSE
csutl-0.2.0.dist-info/METADATA
csutl-0.2.0.dist-info/WHEEL
csutl-0.2.0.dist-info/entry_points.txt
csutl-0.2.0.dist-info/top_level.txt
csutl-0.2.0.dist-info/RECORD
