Metadata-Version: 2.4
Name: csutl
Version: 0.2.0
Summary: CoinSpot Utility
Home-page: https://github.com/archmachina/csutl
Download-URL: https://pypi.org/project/csutl/
Author: Jesse Reichman
License: MIT
Keywords: CoinSpot,Utility
License-File: LICENSE
Requires-Dist: requests>=2.32.0
Dynamic: author
Dynamic: description
Dynamic: description-content-type
Dynamic: download-url
Dynamic: home-page
Dynamic: keywords
Dynamic: license
Dynamic: license-file
Dynamic: requires-dist
Dynamic: summary
